app.py
open_telemetry_generic_v2-0.3.4.dist-info/METADATA
open_telemetry_generic_v2-0.3.4.dist-info/WHEEL
open_telemetry_generic_v2-0.3.4.dist-info/top_level.txt
open_telemetry_generic_v2-0.3.4.dist-info/RECORD
