Metadata-Version: 2.1
Name: open-telemetry-generic-v2
Version: 0.3.4
Summary: A generic function to be able to use for open telemtry cases
Home-page: https://github.com/yourusername/my_package
Author: Atif Agboatwala
Author-email: atif.agboat@hotmail.com
Classifier: Development Status :: 3 - Alpha
Classifier: Intended Audience :: Developers
Classifier: Topic :: Software Development :: Build Tools
Classifier: License :: OSI Approved :: MIT License
Classifier: Programming Language :: Python :: 3
Classifier: Programming Language :: Python :: 3.7
Classifier: Programming Language :: Python :: 3.8
Classifier: Programming Language :: Python :: 3.9
Requires-Dist: opentelemetry-api
